{
  "type": "Feature",
  "properties": {
    "gn:admin1_code":"17",
    "gn:asciiname":"Saint Jean",
    "gn:country_code":"MU",
    "gn:dem":304,
    "gn:feature_class":"P",
    "gn:feature_code":"PPL",
    "gn:name":"Saint Jean",
    "gn:population":0,
    "gn:timezone":"Indian/Mauritius",
    "iso:country":"MU",
    "wof:name":"Saint Jean",
    "wof:placetype":"locality"
},
  "geometry": {"coordinates":[57.48,-20.25028],"type":"Point"}
}