{
  "type": "Feature",
  "properties": {
    "gn:country":"MU",
    "gn:fcode":"PPL",
    "gn:population":17671,
    "iso:country":"MU",
    "name:ceb_x_preferred":[
        "Bel Air Rivi\u00e8re S\u00e8che"
    ],
    "name:eng_x_preferred":[
        "Bel Air Rivi\u00e8re S\u00e8che"
    ],
    "name:fra_x_preferred":[
        "Bel Air Rivi\u00e8re S\u00e8che"
    ],
    "name:heb_x_preferred":[
        "\u05d1\u05dc \u05d0\u05d9\u05d9\u05e8"
    ],
    "name:hun_x_preferred":[
        "Bel Air"
    ],
    "name:hun_x_variant":[
        "Bel Air Rivi\u00e8re S\u00e8che"
    ],
    "name:jpn_x_preferred":[
        "\u30d9\u30eb\u30fb\u30a8\u30a2\u30fb\u30ea\u30d3\u30a8\u30fc\u30eb\u30fb\u30bb\u30b7\u30a7"
    ],
    "name:nld_x_preferred":[
        "Bel Air Rivi\u00e8re S\u00e8che"
    ],
    "name:pol_x_preferred":[
        "Bel Air"
    ],
    "name:swe_x_preferred":[
        "Bel Air Rivi\u00e8re S\u00e8che"
    ],
    "name:zho_x_preferred":[
        "\u8d1d\u83b1\u5c14"
    ],
    "qs:name":"Bel Air",
    "qs:photos_9r":0,
    "qs:photos_sr":0,
    "qs:pop_sr":"6",
    "wd:wordcount":246,
    "wof:name":"Bel Air",
    "wof:placetype":"locality",
    "wof:population":17671
},
  "geometry": {"coordinates":[57.74528,-20.25417],"type":"Point"}
}