{
  "type": "Feature",
  "properties": {
    "gn:admin1_code":"12",
    "gn:asciiname":"Coteau Raffin",
    "gn:cc2":"MU",
    "gn:country_code":"MU",
    "gn:dem":-9999,
    "gn:feature_class":"P",
    "gn:feature_code":"PPL",
    "gn:name":"Coteau Raffin",
    "gn:population":0,
    "gn:timezone":"Indian/Mauritius",
    "iso:country":"MU",
    "name:und_x_variant":[
        "Coteau Rafin",
        "Coteau Raffin"
    ],
    "wof:name":"Coteau Raffin",
    "wof:placetype":"locality"
},
  "geometry": {"coordinates":[57.34528,-20.43389],"type":"Point"}
}