{
  "type": "Feature",
  "properties": {
    "gn:admin1_code":"14",
    "gn:asciiname":"Astroea",
    "gn:cc2":"MU",
    "gn:country_code":"MU",
    "gn:dem":187,
    "gn:feature_class":"P",
    "gn:feature_code":"PPL",
    "gn:name":"Astroea",
    "gn:population":0,
    "gn:timezone":"Indian/Mauritius",
    "iso:country":"MU",
    "name:und_x_variant":[
        "Astr\u00e9a",
        "Astroea"
    ],
    "wof:name":"Astroea",
    "wof:placetype":"locality"
},
  "geometry": {"coordinates":[57.62889000000001,-20.39083],"type":"Point"}
}