{
  "type": "Feature",
  "properties": {
    "gn:admin1_code":"19",
    "gn:asciiname":"Gokoola",
    "gn:cc2":"MU",
    "gn:country_code":"MU",
    "gn:dem":118,
    "gn:feature_class":"P",
    "gn:feature_code":"PPL",
    "gn:name":"Gokoola",
    "gn:population":0,
    "gn:timezone":"Indian/Mauritius",
    "iso:country":"MU",
    "name:und_x_variant":[
        "Gaboola",
        "Gokoola"
    ],
    "wof:name":"Gokoola",
    "wof:placetype":"locality"
},
  "geometry": {"coordinates":[57.64694,-20.10417],"type":"Point"}
}