{
  "type": "Feature",
  "properties": {
    "iso:country":"MU",
    "name:ast_x_preferred":[
        "Aeropuertu Sir Ga\u00ebtan Duval"
    ],
    "name:eng_x_preferred":[
        "Sir Ga\u00ebtan Duval Airport"
    ],
    "name:fas_x_preferred":[
        "\u0641\u0631\u0648\u062f\u06af\u0627\u0647 \u06af\u0627\u0626\u062a\u0627\u0646 \u062f\u0648\u0648\u0627\u0644"
    ],
    "name:fra_x_preferred":[
        "A\u00e9roport de Plaine Corail"
    ],
    "name:ind_x_preferred":[
        "Bandar Udara Pulau Rodrigues"
    ],
    "name:pol_x_preferred":[
        "Port lotniczy Rodrigues"
    ],
    "name:ron_x_preferred":[
        "Aeroportul Sir Ga\u00ebtan Duval"
    ],
    "name:rus_x_preferred":[
        "\u0410\u044d\u0440\u043e\u043f\u043e\u0440\u0442 \u0438\u043c\u0435\u043d\u0438 \u0441\u044d\u0440\u0430 \u0413\u0430\u044d\u0442\u0430\u043d\u0430 \u0414\u044e\u0432\u0430\u043b\u044f"
    ],
    "name:spa_x_preferred":[
        "Aeropuerto Sir Ga\u00ebtan Duval"
    ],
    "name:tgk_x_preferred":[
        "\u0424\u0443\u0440\u0443\u0434\u0433\u043e\u04b3\u0438 \u0433\u043e\u0435\u04b3\u0442\u043e\u043d \u0434\u0443\u0432\u043e\u043b"
    ],
    "oa:elevation_ft":"95",
    "oa:type":"large_airport",
    "woe:hierarchy":{
        "country_id":23424894,
        "planet_id":1,
        "state_id":2346239
    },
    "wof:name":"Rodrigues Plaine Corail Airport",
    "wof:placetype":"campus"
},
  "geometry": {"coordinates":[63.360833333333,-19.7575],"type":"Point"}
}