{
  "type": "Feature",
  "properties": {
    "gn:admin1_code":"16",
    "gn:asciiname":"Le Goulet",
    "gn:country_code":"MU",
    "gn:dem":141,
    "gn:feature_class":"P",
    "gn:feature_code":"PPL",
    "gn:name":"Le Goulet",
    "gn:population":0,
    "gn:timezone":"Indian/Mauritius",
    "iso:country":"MU",
    "wof:name":"Le Goulet",
    "wof:placetype":"locality"
},
  "geometry": {"coordinates":[57.51056,-20.10083],"type":"Point"}
}