{
  "type": "Feature",
  "properties": {
    "gn:admin1_code":"14",
    "gn:asciiname":"Virginia",
    "gn:country_code":"MU",
    "gn:dem":51,
    "gn:feature_class":"P",
    "gn:feature_code":"PPL",
    "gn:name":"Virginia",
    "gn:population":0,
    "gn:timezone":"Indian/Mauritius",
    "iso:country":"MU",
    "wof:name":"Virginia",
    "wof:placetype":"locality"
},
  "geometry": {"coordinates":[57.65583,-20.46778],"type":"Point"}
}