{
  "type": "Feature",
  "properties": {
    "gn:admin1_code":"20",
    "gn:asciiname":"Senneville",
    "gn:country_code":"MU",
    "gn:dem":92,
    "gn:feature_class":"P",
    "gn:feature_code":"PPL",
    "gn:name":"Senneville",
    "gn:population":0,
    "gn:timezone":"Indian/Mauritius",
    "iso:country":"MU",
    "wof:name":"Senneville",
    "wof:placetype":"locality"
},
  "geometry": {"coordinates":[57.55,-20.50111],"type":"Point"}
}