{
  "type": "Feature",
  "properties": {
    "gn:admin1_code":"15",
    "gn:asciiname":"Riviere Baptiste",
    "gn:country_code":"MU",
    "gn:dem":406,
    "gn:feature_class":"P",
    "gn:feature_code":"PPL",
    "gn:name":"Rivi\u00e8re Baptiste",
    "gn:population":0,
    "gn:timezone":"Indian/Mauritius",
    "iso:country":"MU",
    "wof:name":"Riviere Baptiste",
    "wof:placetype":"locality"
},
  "geometry": {"coordinates":[57.52778000000001,-20.20611],"type":"Point"}
}