{
  "type": "Feature",
  "properties": {
    "gn:asciiname":"La Nicoliere",
    "gn:country_code":"MU",
    "gn:dem":252,
    "gn:feature_class":"P",
    "gn:feature_code":"PPL",
    "gn:name":"La Nicoliere",
    "gn:population":0,
    "gn:timezone":"Indian/Mauritius",
    "iso:country":"MU",
    "wof:name":"La Nicoliere",
    "wof:placetype":"locality"
},
  "geometry": {"coordinates":[57.61699,-20.15757],"type":"Point"}
}