{
  "type": "Feature",
  "properties": {
    "gn:admin1_code":"16",
    "gn:asciiname":"Pointe aux Canonniers",
    "gn:cc2":"MU",
    "gn:country_code":"MU",
    "gn:dem":6,
    "gn:feature_class":"P",
    "gn:feature_code":"PPL",
    "gn:name":"Pointe aux Canonniers",
    "gn:population":0,
    "gn:timezone":"Indian/Mauritius",
    "iso:country":"MU",
    "name:und_x_variant":[
        "Pointe aux Cannoniers",
        "Pointe aux Canonniers"
    ],
    "wof:name":"Pointe aux Canonniers",
    "wof:placetype":"locality"
},
  "geometry": {"coordinates":[57.56,-20.00833],"type":"Point"}
}