{
  "type": "Feature",
  "properties": {
    "gn:admin1_code":"18",
    "gn:asciiname":"Abercrombie",
    "gn:country_code":"MU",
    "gn:dem":23,
    "gn:feature_class":"P",
    "gn:feature_code":"PPL",
    "gn:name":"Abercrombie",
    "gn:population":0,
    "gn:timezone":"Indian/Mauritius",
    "iso:country":"MU",
    "wof:name":"Abercrombie",
    "wof:placetype":"locality"
},
  "geometry": {"coordinates":[57.51611,-20.14806],"type":"Point"}
}