{
  "type": "Feature",
  "properties": {
    "gn:admin1_code":"18",
    "gn:asciiname":"Abercrombie",
    "gn:country_code":"MU",
    "gn:dem":23,
    "gn:feature_class":"P",
    "gn:feature_code":"PPL",
    "gn:name":"Abercrombie",
    "gn:population":0,
    "gn:timezone":"Indian/Mauritius",
    "iso:country":"MU",
    "name:ces_x_preferred":[
        "Abercrombie"
    ],
    "name:deu_x_preferred":[
        "Abercrombie"
    ],
    "name:fin_x_preferred":[
        "Abercrombie"
    ],
    "name:fra_x_preferred":[
        "Abercrombie"
    ],
    "name:heb_x_preferred":[
        "\u05d0\u05d1\u05e8\u05e7\u05e8\u05d5\u05de\u05d1\u05d9"
    ],
    "name:ita_x_preferred":[
        "Abercrombie"
    ],
    "name:jpn_x_preferred":[
        "\u30a2\u30d0\u30fc\u30af\u30ed\u30f3\u30d3\u30fc"
    ],
    "name:kor_x_preferred":[
        "\uc560\ubc84\ud06c\ub86c\ube44"
    ],
    "name:nds_x_preferred":[
        "Abercrombie"
    ],
    "name:nld_x_preferred":[
        "Abercrombie"
    ],
    "name:pol_x_preferred":[
        "Abercrombie"
    ],
    "name:por_x_preferred":[
        "Abercrombie"
    ],
    "name:rus_x_preferred":[
        "\u0410\u0431\u0435\u0440\u043a\u0440\u043e\u043c\u0431\u0438"
    ],
    "name:spa_x_preferred":[
        "Abercrombie"
    ],
    "name:swe_x_preferred":[
        "Abercrombie"
    ],
    "name:ukr_x_preferred":[
        "\u0415\u0431\u0435\u0440\u043a\u0440\u043e\u043c\u0431\u0456"
    ],
    "wof:name":"Abercrombie",
    "wof:placetype":"locality"
},
  "geometry": {"coordinates":[57.51611,-20.14806],"type":"Point"}
}