{
  "type": "Feature",
  "properties": {
    "gn:admin1_code":"14",
    "gn:asciiname":"Beau Site",
    "gn:country_code":"MU",
    "gn:dem":147,
    "gn:feature_class":"P",
    "gn:feature_code":"PPL",
    "gn:name":"Beau Site",
    "gn:population":0,
    "gn:timezone":"Indian/Mauritius",
    "iso:country":"MU",
    "wof:name":"Beau Site",
    "wof:placetype":"locality"
},
  "geometry": {"coordinates":[57.66333,-20.36778],"type":"Point"}
}