{
  "type": "Feature",
  "properties": {
    "gn:admin1_code":"20",
    "gn:asciiname":"Mont Blanc",
    "gn:country_code":"MU",
    "gn:dem":163,
    "gn:feature_class":"P",
    "gn:feature_code":"PPL",
    "gn:name":"Mont Blanc",
    "gn:population":0,
    "gn:timezone":"Indian/Mauritius",
    "iso:country":"MU",
    "wof:name":"Mont Blanc",
    "wof:placetype":"locality"
},
  "geometry": {"coordinates":[57.47444,-20.47889],"type":"Point"}
}