{
  "type": "Feature",
  "properties": {
    "gn:admin1_code":"14",
    "gn:asciiname":"Cent Gaulettes",
    "gn:country_code":"MU",
    "gn:dem":212,
    "gn:feature_class":"P",
    "gn:feature_code":"PPL",
    "gn:name":"Cent Gaulettes",
    "gn:population":0,
    "gn:timezone":"Indian/Mauritius",
    "iso:country":"MU",
    "wof:name":"Cent Gaulettes",
    "wof:placetype":"locality"
},
  "geometry": {"coordinates":[57.64471999999999,-20.37167],"type":"Point"}
}