{
  "type": "Feature",
  "properties": {
    "gn:country":"MU",
    "gn:fcode":"PPL",
    "gn:population":4803,
    "iso:country":"MU",
    "name:ast_x_preferred":[
        "Cap Malheureux"
    ],
    "name:ceb_x_preferred":[
        "Cap Malheureux"
    ],
    "name:deu_x_preferred":[
        "Cap Malheureux"
    ],
    "name:eng_x_preferred":[
        "Cap Malheureux"
    ],
    "name:fra_x_preferred":[
        "Cap Malheureux"
    ],
    "name:nld_x_preferred":[
        "Cap Malheureux"
    ],
    "name:swe_x_preferred":[
        "Cap Malheureux"
    ],
    "name:zho_x_preferred":[
        "\u99ac\u52d2\u52d2\u89d2"
    ],
    "qs:name":"Cap Malheureux",
    "qs:photos_9r":0,
    "qs:photos_sr":0,
    "qs:pop_sr":"4",
    "wd:wordcount":228,
    "wof:name":"Cap Malheureux",
    "wof:placetype":"locality",
    "wof:population":4803
},
  "geometry": {"coordinates":[57.61417,-19.98417],"type":"Point"}
}