{
  "type": "Feature",
  "properties": {
    "gn:admin1_code":"15",
    "gn:asciiname":"La Laura",
    "gn:country_code":"MU",
    "gn:dem":428,
    "gn:feature_class":"P",
    "gn:feature_code":"PPL",
    "gn:name":"La Laura",
    "gn:population":0,
    "gn:timezone":"Indian/Mauritius",
    "iso:country":"MU",
    "wof:name":"La Laura",
    "wof:placetype":"locality"
},
  "geometry": {"coordinates":[57.54556,-20.20028],"type":"Point"}
}