{
  "type": "Feature",
  "properties": {
    "gn:admin1_code":"15",
    "gn:asciiname":"Minissy",
    "gn:country_code":"MU",
    "gn:dem":324,
    "gn:feature_class":"P",
    "gn:feature_code":"PPL",
    "gn:name":"Minissy",
    "gn:population":0,
    "gn:timezone":"Indian/Mauritius",
    "iso:country":"MU",
    "wof:name":"Minissy",
    "wof:placetype":"locality"
},
  "geometry": {"coordinates":[57.50666999999999,-20.2375],"type":"Point"}
}