{
  "type": "Feature",
  "properties": {
    "gn:admin1_code":"19",
    "gn:asciiname":"Belmont",
    "gn:country_code":"MU",
    "gn:dem":38,
    "gn:feature_class":"P",
    "gn:feature_code":"PPL",
    "gn:name":"Belmont",
    "gn:population":0,
    "gn:timezone":"Indian/Mauritius",
    "iso:country":"MU",
    "wof:name":"Belmont",
    "wof:placetype":"locality"
},
  "geometry": {"coordinates":[57.65861,-20.045],"type":"Point"}
}