{
  "type": "Feature",
  "properties": {
    "gn:admin1_code":"13",
    "gn:asciiname":"Trois Ilots",
    "gn:country_code":"MU",
    "gn:dem":83,
    "gn:feature_class":"P",
    "gn:feature_code":"PPL",
    "gn:name":"Trois \u00celots",
    "gn:population":0,
    "gn:timezone":"Indian/Mauritius",
    "iso:country":"MU",
    "wof:name":"Trois Ilots",
    "wof:placetype":"locality"
},
  "geometry": {"coordinates":[57.73806,-20.26667],"type":"Point"}
}