{
  "type": "Feature",
  "properties": {
    "gn:country":"MU",
    "gn:fcode":"PPL",
    "gn:pop":1525,
    "iso:country":"MU",
    "qs:name":"Petite Case Noyale",
    "qs:photos_9r":0,
    "qs:photos_sr":0,
    "qs:pop_sr":"3",
    "wof:name":"Petite Case Noyale",
    "wof:placetype":"locality",
    "wof:population":1525
},
  "geometry": {"coordinates":[57.365,-20.39306],"type":"Point"}
}