{
  "type": "Feature",
  "properties": {
    "gn:admin1_code":"13",
    "gn:asciiname":"Coquinbourg",
    "gn:country_code":"MU",
    "gn:dem":333,
    "gn:feature_class":"P",
    "gn:feature_code":"PPL",
    "gn:name":"Coquinbourg",
    "gn:population":0,
    "gn:timezone":"Indian/Mauritius",
    "iso:country":"MU",
    "wof:name":"Coquinbourg",
    "wof:placetype":"locality"
},
  "geometry": {"coordinates":[57.63806,-20.23778],"type":"Point"}
}