{
  "type": "Feature",
  "properties": {
    "gn:admin1_code":"13",
    "gn:asciiname":"L'Unite",
    "gn:country_code":"MU",
    "gn:dem":251,
    "gn:feature_class":"P",
    "gn:feature_code":"PPL",
    "gn:name":"L\u2019Unit\u00e9",
    "gn:population":0,
    "gn:timezone":"Indian/Mauritius",
    "iso:country":"MU",
    "name:und_x_variant":[
        "Unit\u00e9",
        "L\u2019Unit\u00e9"
    ],
    "wof:name":"L'Unite",
    "wof:placetype":"locality"
},
  "geometry": {"coordinates":[57.66721999999999,-20.23278],"type":"Point"}
}