{
  "type": "Feature",
  "properties": {
    "gn:admin1_code":"23",
    "gn:asciiname":"Citron Donis",
    "gn:country_code":"MU",
    "gn:dem":257,
    "gn:feature_class":"P",
    "gn:feature_code":"PPL",
    "gn:name":"Citron Donis",
    "gn:population":0,
    "gn:timezone":"Indian/Mauritius",
    "iso:country":"MU",
    "wof:name":"Citron Donis",
    "wof:placetype":"locality"
},
  "geometry": {"coordinates":[63.41667,-19.72917],"type":"Point"}
}