{
  "type": "Feature",
  "properties": {
    "gn:admin1_code":"17",
    "gn:asciiname":"Belle Etoile",
    "gn:country_code":"MU",
    "gn:dem":108,
    "gn:feature_class":"P",
    "gn:feature_code":"PPL",
    "gn:name":"Belle \u00c9toile",
    "gn:population":0,
    "gn:timezone":"Indian/Mauritius",
    "iso:country":"MU",
    "wof:name":"Belle Etoile",
    "wof:placetype":"locality"
},
  "geometry": {"coordinates":[57.46417,-20.20167],"type":"Point"}
}