{
  "type": "Feature",
  "properties": {
    "gn:admin1_code":"16",
    "gn:asciiname":"Solitude",
    "gn:country_code":"MU",
    "gn:dem":30,
    "gn:feature_class":"P",
    "gn:feature_code":"PPL",
    "gn:name":"Solitude",
    "gn:population":0,
    "gn:timezone":"Indian/Mauritius",
    "iso:country":"MU",
    "name:ara_x_preferred":[
        "\u0639\u0632\u0644\u0629"
    ],
    "name:bul_x_preferred":[
        "\u0421\u0430\u043c\u043e\u0442\u0430"
    ],
    "name:ces_x_preferred":[
        "Samota"
    ],
    "name:epo_x_preferred":[
        "Soleco"
    ],
    "name:fra_x_preferred":[
        "Solitude"
    ],
    "name:glg_x_preferred":[
        "Soidade"
    ],
    "name:heb_x_preferred":[
        "\u05d4\u05ea\u05d1\u05d5\u05d3\u05d3\u05d5\u05ea"
    ],
    "name:ind_x_preferred":[
        "Kesendirian"
    ],
    "name:ita_x_preferred":[
        "Solitudine"
    ],
    "name:lat_x_preferred":[
        "Solitudo"
    ],
    "name:lit_x_preferred":[
        "Vienatv\u0117"
    ],
    "name:pnb_x_preferred":[
        "\u0642\u0644\u0639\u06c1 \u0633\u0648\u0644\u06cc\u0686\u06cc\u0648\u0688"
    ],
    "name:por_x_preferred":[
        "Solitude"
    ],
    "name:ron_x_preferred":[
        "Singur\u0103tate"
    ],
    "name:spa_x_preferred":[
        "Soledad"
    ],
    "name:sqi_x_preferred":[
        "Vetmia"
    ],
    "name:tam_x_preferred":[
        "\u0ba4\u0ba9\u0bbf\u0bae\u0bc8"
    ],
    "name:vie_x_preferred":[
        "\u0110\u01a1n \u0111\u1ed9c"
    ],
    "name:yid_x_preferred":[
        "\u05d4\u05ea\u05d1\u05d5\u05d3\u05d3\u05d5\u05ea"
    ],
    "wof:name":"Solitude",
    "wof:placetype":"locality"
},
  "geometry": {"coordinates":[57.53861,-20.07694],"type":"Point"}
}