{
  "type": "Feature",
  "properties": {
    "gn:admin1_code":"16",
    "gn:asciiname":"Solitude",
    "gn:country_code":"MU",
    "gn:dem":30,
    "gn:feature_class":"P",
    "gn:feature_code":"PPL",
    "gn:name":"Solitude",
    "gn:population":0,
    "gn:timezone":"Indian/Mauritius",
    "iso:country":"MU",
    "wof:name":"Solitude",
    "wof:placetype":"locality"
},
  "geometry": {"coordinates":[57.53861,-20.07694],"type":"Point"}
}