{
  "type": "Feature",
  "properties": {
    "gn:admin1_code":"17",
    "gn:asciiname":"Mesnil",
    "gn:country_code":"MU",
    "gn:dem":441,
    "gn:feature_class":"P",
    "gn:feature_code":"PPL",
    "gn:name":"Mesnil",
    "gn:population":0,
    "gn:timezone":"Indian/Mauritius",
    "iso:country":"MU",
    "name:bre_x_preferred":[
        "Mesnil"
    ],
    "name:ceb_x_preferred":[
        "Mesnil"
    ],
    "name:deu_x_preferred":[
        "Mesnil"
    ],
    "name:fra_x_preferred":[
        "Mesnil"
    ],
    "name:ita_x_preferred":[
        "Mesnil"
    ],
    "name:nld_x_preferred":[
        "Mesnil"
    ],
    "name:nrm_x_preferred":[
        "M\u00eani"
    ],
    "name:pms_x_preferred":[
        "Mesnil"
    ],
    "name:por_x_preferred":[
        "Mesnil"
    ],
    "name:rus_x_preferred":[
        "\u041c\u0435\u043d\u0438\u043b\u044c"
    ],
    "name:spa_x_preferred":[
        "Mesnil"
    ],
    "name:swe_x_preferred":[
        "Mesnil"
    ],
    "name:zho_x_preferred":[
        "\u6885\u5c3c\u52d2"
    ],
    "wof:name":"Mesnil",
    "wof:placetype":"locality"
},
  "geometry": {"coordinates":[57.51167,-20.29028],"type":"Point"}
}