{
  "type": "Feature",
  "properties": {
    "gn:admin1_code":"20",
    "gn:asciiname":"Saint Felix",
    "gn:country_code":"MU",
    "gn:dem":133,
    "gn:feature_class":"P",
    "gn:feature_code":"PPL",
    "gn:name":"Saint F\u00e9lix",
    "gn:population":0,
    "gn:timezone":"Indian/Mauritius",
    "iso:country":"MU",
    "wof:name":"Saint Felix",
    "wof:placetype":"locality"
},
  "geometry": {"coordinates":[57.56639000000001,-20.48667],"type":"Point"}
}