{
  "type": "Feature",
  "properties": {
    "gn:admin1_code":"20",
    "gn:asciiname":"Benares",
    "gn:country_code":"MU",
    "gn:dem":86,
    "gn:feature_class":"P",
    "gn:feature_code":"PPL",
    "gn:name":"B\u00e9nar\u00e8s",
    "gn:population":0,
    "gn:timezone":"Indian/Mauritius",
    "iso:country":"MU",
    "wof:name":"Benares",
    "wof:placetype":"locality"
},
  "geometry": {"coordinates":[57.58306,-20.49694],"type":"Point"}
}