{
  "type": "Feature",
  "properties": {
    "gn:admin1_code":"16",
    "gn:asciiname":"Beau Plan",
    "gn:country_code":"MU",
    "gn:dem":62,
    "gn:feature_class":"P",
    "gn:feature_code":"PPL",
    "gn:name":"Beau Plan",
    "gn:population":0,
    "gn:timezone":"Indian/Mauritius",
    "iso:country":"MU",
    "wof:name":"Beau Plan",
    "wof:placetype":"locality"
},
  "geometry": {"coordinates":[57.56833,-20.09417],"type":"Point"}
}