{
  "type": "Feature",
  "properties": {
    "gn:admin1_code":"13",
    "gn:asciiname":"La Commune",
    "gn:country_code":"MU",
    "gn:dem":124,
    "gn:feature_class":"P",
    "gn:feature_code":"PPL",
    "gn:name":"La Commune",
    "gn:population":0,
    "gn:timezone":"Indian/Mauritius",
    "iso:country":"MU",
    "wof:name":"La Commune",
    "wof:placetype":"locality"
},
  "geometry": {"coordinates":[57.72083000000001,-20.30833],"type":"Point"}
}