{
  "type": "Feature",
  "properties": {
    "gn:admin1_code":"00",
    "gn:asciiname":"Paves",
    "gn:country_code":"MU",
    "gn:dem":48,
    "gn:feature_class":"P",
    "gn:feature_code":"PPL",
    "gn:name":"Paves",
    "gn:population":0,
    "gn:timezone":"Indian/Mauritius",
    "iso:country":"MU",
    "wof:name":"Paves",
    "wof:placetype":"locality"
},
  "geometry": {"coordinates":[63.45,-19.68333],"type":"Point"}
}