{
  "type": "Feature",
  "properties": {
    "gn:admin1_code":"19",
    "gn:asciiname":"Ile d'Ambre",
    "gn:country_code":"MU",
    "gn:dem":20,
    "gn:feature_class":"P",
    "gn:feature_code":"PPL",
    "gn:name":"\u00cele d\u2019Ambre",
    "gn:population":0,
    "gn:timezone":"Indian/Mauritius",
    "iso:country":"MU",
    "wof:name":"Ile d'Ambre",
    "wof:placetype":"locality"
},
  "geometry": {"coordinates":[57.68028,-20.07417],"type":"Point"}
}