{
  "type": "Feature",
  "properties": {
    "gn:admin1_code":"15",
    "gn:asciiname":"Montebello",
    "gn:country_code":"MU",
    "gn:dem":114,
    "gn:feature_class":"P",
    "gn:feature_code":"PPL",
    "gn:name":"Montebello",
    "gn:population":0,
    "gn:timezone":"Indian/Mauritius",
    "iso:country":"MU",
    "wof:name":"Montebello",
    "wof:placetype":"locality"
},
  "geometry": {"coordinates":[57.47528000000001,-20.19917],"type":"Point"}
}