{
  "type": "Feature",
  "properties": {
    "gn:country":"MU",
    "gn:fcode":"PPL",
    "gn:pop":4218,
    "iso:country":"MU",
    "qs:name":"Plaines des Roches",
    "qs:photos_9r":0,
    "qs:photos_sr":0,
    "qs:pop_sr":"4",
    "wd:wordcount":235,
    "wof:name":"Plaines des Roches",
    "wof:placetype":"locality",
    "wof:population":4218
},
  "geometry": {"coordinates":[57.69083,-20.11167],"type":"Point"}
}