{
  "type": "Feature",
  "properties": {
    "gn:admin1_code":"13",
    "gn:asciiname":"Bois d'Oiseaux",
    "gn:country_code":"MU",
    "gn:dem":118,
    "gn:feature_class":"P",
    "gn:feature_code":"PPL",
    "gn:name":"Bois d\u2019Oiseaux",
    "gn:population":0,
    "gn:timezone":"Indian/Mauritius",
    "iso:country":"MU",
    "name:und_x_variant":[
        "Bois d\u2019Oiseau",
        "Bois d\u2019Oiseaux"
    ],
    "wof:name":"Bois d'Oiseaux",
    "wof:placetype":"locality"
},
  "geometry": {"coordinates":[57.735,-20.29778],"type":"Point"}
}