{
  "type": "Feature",
  "properties": {
    "gn:admin1_code":"17",
    "gn:asciiname":"La Source",
    "gn:country_code":"MU",
    "gn:dem":364,
    "gn:feature_class":"P",
    "gn:feature_code":"PPL",
    "gn:name":"La Source",
    "gn:population":0,
    "gn:timezone":"Indian/Mauritius",
    "iso:country":"MU",
    "wof:name":"La Source",
    "wof:placetype":"locality"
},
  "geometry": {"coordinates":[57.45667,-20.2675],"type":"Point"}
}