{
  "type": "Feature",
  "properties": {
    "gn:admin1_code":"14",
    "gn:asciiname":"Dalais",
    "gn:country_code":"MU",
    "gn:dem":68,
    "gn:feature_class":"P",
    "gn:feature_code":"PPL",
    "gn:name":"Dalais",
    "gn:population":0,
    "gn:timezone":"Indian/Mauritius",
    "iso:country":"MU",
    "wof:name":"Dalais",
    "wof:placetype":"locality"
},
  "geometry": {"coordinates":[57.68528000000001,-20.39722],"type":"Point"}
}