{
  "type": "Feature",
  "properties": {
    "gn:admin1_code":"19",
    "gn:asciiname":"Poudre d'Or",
    "gn:country_code":"MU",
    "gn:dem":16,
    "gn:feature_class":"P",
    "gn:feature_code":"PPL",
    "gn:name":"Poudre d\u2019Or",
    "gn:population":0,
    "gn:timezone":"Indian/Mauritius",
    "iso:country":"MU",
    "name:und_x_variant":[
        "Poudre D\u2019Or Village",
        "Poudre d\u2019Or"
    ],
    "wof:name":"Poudre d'Or",
    "wof:placetype":"locality"
},
  "geometry": {"coordinates":[57.67667,-20.06],"type":"Point"}
}