{
  "type": "Feature",
  "properties": {
    "gn:admin1_code":"16",
    "gn:asciiname":"Bois Rouge",
    "gn:country_code":"MU",
    "gn:dem":69,
    "gn:feature_class":"P",
    "gn:feature_code":"PPL",
    "gn:name":"Bois Rouge",
    "gn:population":0,
    "gn:timezone":"Indian/Mauritius",
    "iso:country":"MU",
    "wof:name":"Bois Rouge",
    "wof:placetype":"locality"
},
  "geometry": {"coordinates":[57.58306,-20.08139],"type":"Point"}
}