{
  "type": "Feature",
  "properties": {
    "gn:admin1_code":"13",
    "gn:asciiname":"Camp de Masque Pave",
    "gn:country_code":"MU",
    "gn:dem":234,
    "gn:feature_class":"P",
    "gn:feature_code":"PPL",
    "gn:name":"Camp de Masque Pave",
    "gn:population":0,
    "gn:timezone":"Indian/Mauritius",
    "iso:country":"MU",
    "wof:name":"Camp de Masque Pave",
    "wof:placetype":"locality"
},
  "geometry": {"coordinates":[57.675,-20.23611],"type":"Point"}
}