{
  "type": "Feature",
  "properties": {
    "gn:asciiname":"Bain Boeuf",
    "gn:country_code":"MU",
    "gn:dem":9,
    "gn:feature_class":"P",
    "gn:feature_code":"PPL",
    "gn:name":"Bain Boeuf",
    "gn:population":0,
    "gn:timezone":"Indian/Mauritius",
    "iso:country":"MU",
    "wof:name":"Bain Boeuf",
    "wof:placetype":"locality"
},
  "geometry": {"coordinates":[57.60617,-19.98767],"type":"Point"}
}