{
  "type": "Feature",
  "properties": {
    "gn:admin1_code":"13",
    "gn:asciiname":"Deux Freres",
    "gn:country_code":"MU",
    "gn:dem":161,
    "gn:feature_class":"P",
    "gn:feature_code":"PPL",
    "gn:name":"Deux Fr\u00e8res",
    "gn:population":0,
    "gn:timezone":"Indian/Mauritius",
    "iso:country":"MU",
    "wof:name":"Deux Freres",
    "wof:placetype":"locality"
},
  "geometry": {"coordinates":[57.77111,-20.28667],"type":"Point"}
}