{
  "type": "Feature",
  "properties": {
    "gn:admin1_code":"13",
    "gn:asciiname":"Isidore Rose",
    "gn:country_code":"MU",
    "gn:dem":55,
    "gn:feature_class":"P",
    "gn:feature_code":"PPL",
    "gn:name":"Isidore Rose",
    "gn:population":0,
    "gn:timezone":"Indian/Mauritius",
    "iso:country":"MU",
    "wof:name":"Isidore Rose",
    "wof:placetype":"locality"
},
  "geometry": {"coordinates":[57.74806,-20.20778],"type":"Point"}
}