{
  "type": "Feature",
  "properties": {
    "gn:admin1_code":"00",
    "gn:asciiname":"Trefles",
    "gn:country_code":"MU",
    "gn:dem":47,
    "gn:feature_class":"P",
    "gn:feature_code":"PPL",
    "gn:name":"Tr\u00e8fles",
    "gn:population":0,
    "gn:timezone":"Indian/Mauritius",
    "iso:country":"MU",
    "wof:name":"Trefles",
    "wof:placetype":"locality"
},
  "geometry": {"coordinates":[63.46666999999999,-19.68333],"type":"Point"}
}