{
  "type": "Feature",
  "properties": {
    "gn:asciiname":"Belle Rive",
    "gn:country_code":"MU",
    "gn:dem":567,
    "gn:feature_class":"P",
    "gn:feature_code":"PPL",
    "gn:name":"Belle Rive",
    "gn:population":0,
    "gn:timezone":"Indian/Mauritius",
    "iso:country":"MU",
    "wof:name":"Belle Rive",
    "wof:placetype":"locality"
},
  "geometry": {"coordinates":[57.55244,-20.34786],"type":"Point"}
}