{
  "type": "Feature",
  "properties": {
    "gn:admin1_code":"17",
    "gn:asciiname":"Vuillemain",
    "gn:country_code":"MU",
    "gn:dem":202,
    "gn:feature_class":"P",
    "gn:feature_code":"PPL",
    "gn:name":"Vuillemain",
    "gn:population":0,
    "gn:timezone":"Indian/Mauritius",
    "iso:country":"MU",
    "wof:name":"Vuillemain",
    "wof:placetype":"locality"
},
  "geometry": {"coordinates":[57.46639,-20.215],"type":"Point"}
}