{
  "type": "Feature",
  "properties": {
    "iso:country":"MU",
    "name:eng_x_preferred":[
        "Rose-Belle"
    ],
    "name:fra_x_preferred":[
        "Rose-Belle"
    ],
    "name:nld_x_preferred":[
        "Rose-Belle"
    ],
    "name:pol_x_preferred":[
        "Rose Belle"
    ],
    "name:ron_x_preferred":[
        "Rose-Belle"
    ],
    "name:rus_x_preferred":[
        "\u0420\u043e\u0437-\u0411\u0435\u043b\u044c"
    ],
    "qs:gn_country":"MU",
    "qs:gn_fcode":"PPLA",
    "qs:gn_pop":12619,
    "qs:name":"Rose Belle",
    "qs:name_adm0":"Mauritius",
    "qs:name_adm1":"Grand Port",
    "qs:photos":128,
    "qs:photos_1k":26,
    "qs:photos_9k":1,
    "qs:photos_9r":3,
    "qs:photos_all":128,
    "qs:photos_sr":3,
    "qs:placetype":"Town",
    "qs:pop_sr":"6",
    "qs:woe_adm0":23424894,
    "wd:wordcount":62,
    "wof:name":"Rose Belle",
    "wof:placetype":"locality",
    "wof:population":12619
},
  "geometry": {"coordinates":[57.59667,-20.40028],"type":"Point"}
}