{
  "type": "Feature",
  "properties": {
    "gn:admin1_code":"19",
    "gn:asciiname":"Labourdonnais",
    "gn:country_code":"MU",
    "gn:dem":89,
    "gn:feature_class":"P",
    "gn:feature_code":"PPL",
    "gn:name":"Labourdonnais",
    "gn:population":0,
    "gn:timezone":"Indian/Mauritius",
    "iso:country":"MU",
    "wof:name":"Labourdonnais",
    "wof:placetype":"locality"
},
  "geometry": {"coordinates":[57.61,-20.06833],"type":"Point"}
}