{
  "type": "Feature",
  "properties": {
    "gn:country":"MU",
    "gn:fcode":"PPL",
    "gn:population":5745,
    "iso:country":"MU",
    "qs:name":"Sebastopol",
    "qs:photos_9r":0,
    "qs:photos_sr":0,
    "qs:pop_sr":"5",
    "wd:wordcount":129,
    "wof:name":"Sebastopol",
    "wof:placetype":"locality",
    "wof:population":5745
},
  "geometry": {"coordinates":[57.6875,-20.28889],"type":"Point"}
}