{
  "type": "Feature",
  "properties": {
    "gn:admin1_code":"13",
    "gn:asciiname":"Pellegrin",
    "gn:country_code":"MU",
    "gn:dem":255,
    "gn:feature_class":"P",
    "gn:feature_code":"PPL",
    "gn:name":"Pellegrin",
    "gn:population":0,
    "gn:timezone":"Indian/Mauritius",
    "iso:country":"MU",
    "wof:name":"Pellegrin",
    "wof:placetype":"locality"
},
  "geometry": {"coordinates":[57.67916999999999,-20.2775],"type":"Point"}
}