{
  "type": "Feature",
  "properties": {
    "gn:admin1_code":"13",
    "gn:asciiname":"Pellegrin",
    "gn:country_code":"MU",
    "gn:dem":255,
    "gn:feature_class":"P",
    "gn:feature_code":"PPL",
    "gn:name":"Pellegrin",
    "gn:population":0,
    "gn:timezone":"Indian/Mauritius",
    "iso:country":"MU",
    "name:deu_x_preferred":[
        "Pellegrin"
    ],
    "name:fra_x_preferred":[
        "Pellegrin"
    ],
    "name:ita_x_preferred":[
        "Pellegrin"
    ],
    "name:rus_x_preferred":[
        "\u041f\u0435\u043b\u043b\u0435\u0433\u0440\u0435\u043d"
    ],
    "name:swe_x_preferred":[
        "Pellegrin"
    ],
    "wof:name":"Pellegrin",
    "wof:placetype":"locality"
},
  "geometry": {"coordinates":[57.67916999999999,-20.2775],"type":"Point"}
}