{
  "type": "Feature",
  "properties": {
    "gn:admin1_code":"20",
    "gn:asciiname":"Baie du Cap",
    "gn:country_code":"MU",
    "gn:dem":149,
    "gn:feature_class":"P",
    "gn:feature_code":"PPL",
    "gn:name":"Baie du Cap",
    "gn:population":0,
    "gn:timezone":"Indian/Mauritius",
    "iso:country":"MU",
    "name:rus_x_preferred":[
        "\u0411\u0435-\u0434\u044e-\u041a\u0430\u043f"
    ],
    "wof:name":"Baie du Cap",
    "wof:placetype":"locality"
},
  "geometry": {"coordinates":[57.37056,-20.48833],"type":"Point"}
}