{
  "type": "Feature",
  "properties": {
    "gn:admin1_code":"15",
    "gn:asciiname":"Valetta",
    "gn:country_code":"MU",
    "gn:dem":451,
    "gn:feature_class":"P",
    "gn:feature_code":"PPL",
    "gn:name":"Valetta",
    "gn:population":0,
    "gn:timezone":"Indian/Mauritius",
    "iso:country":"MU",
    "wof:name":"Valetta",
    "wof:placetype":"locality"
},
  "geometry": {"coordinates":[57.56536,-20.25664],"type":"Point"}
}