{
  "type": "Feature",
  "properties": {
    "iso:country":"MU",
    "name:und_x_variant":[
        "Pailles Village"
    ],
    "qs:gn_country":"MU",
    "qs:gn_fcode":"PPL",
    "qs:gn_pop":10622,
    "qs:name":"Pailles",
    "qs:name_adm0":"Mauritius",
    "qs:name_adm1":"Port Louis",
    "qs:photos":173,
    "qs:photos_1k":35,
    "qs:photos_9k":1,
    "qs:photos_9r":4,
    "qs:photos_all":173,
    "qs:photos_sr":4,
    "qs:placetype":"Town",
    "qs:pop_sr":"6",
    "qs:woe_adm0":23424894,
    "wof:name":"Pailles",
    "wof:placetype":"locality",
    "wof:population":10622
},
  "geometry": {"coordinates":[57.48826,-20.19271],"type":"Point"}
}