{
  "type": "Feature",
  "properties": {
    "gn:admin1_code":"15",
    "gn:asciiname":"L'Assurance",
    "gn:country_code":"MU",
    "gn:dem":436,
    "gn:feature_class":"P",
    "gn:feature_code":"PPL",
    "gn:name":"L\u2019Assurance",
    "gn:population":0,
    "gn:timezone":"Indian/Mauritius",
    "iso:country":"MU",
    "wof:name":"L'Assurance",
    "wof:placetype":"locality"
},
  "geometry": {"coordinates":[57.54722,-20.24972],"type":"Point"}
}