{
  "type": "Feature",
  "properties": {
    "gn:admin1_code":"14",
    "gn:asciiname":"Pointe d'Esny",
    "gn:country_code":"MU",
    "gn:dem":10,
    "gn:feature_class":"P",
    "gn:feature_code":"PPL",
    "gn:name":"Pointe d\u2019Esny",
    "gn:population":0,
    "gn:timezone":"Indian/Mauritius",
    "iso:country":"MU",
    "wof:name":"Pointe d'Esny",
    "wof:placetype":"locality"
},
  "geometry": {"coordinates":[57.72693,-20.43035],"type":"Point"}
}