{
  "type": "Feature",
  "properties": {
    "gn:admin1_code":"19",
    "gn:asciiname":"Belle Vue Maurel",
    "gn:cc2":"MU",
    "gn:country_code":"MU",
    "gn:dem":108,
    "gn:feature_class":"P",
    "gn:feature_code":"PPL",
    "gn:name":"Belle Vue Maurel",
    "gn:population":0,
    "gn:timezone":"Indian/Mauritius",
    "iso:country":"MU",
    "name:fra_x_preferred":[
        "Belle Vue Maurel"
    ],
    "name:ita_x_preferred":[
        "Belle Vue Maurel"
    ],
    "name:spa_x_preferred":[
        "Belle Vue Maurel"
    ],
    "name:und_x_variant":[
        "Belle Vue"
    ],
    "wof:name":"Belle Vue Maurel",
    "wof:placetype":"locality"
},
  "geometry": {"coordinates":[57.66361,-20.12028],"type":"Point"}
}