{
  "type": "Feature",
  "properties": {
    "gn:admin1_code":"20",
    "gn:asciiname":"Luchon",
    "gn:cc2":"MU",
    "gn:country_code":"MU",
    "gn:dem":215,
    "gn:feature_class":"P",
    "gn:feature_code":"PPL",
    "gn:name":"Luchon",
    "gn:population":0,
    "gn:timezone":"Indian/Mauritius",
    "iso:country":"MU",
    "name:und_x_variant":[
        "Lu\u00e7on",
        "Luchon"
    ],
    "wof:name":"Luchon",
    "wof:placetype":"locality"
},
  "geometry": {"coordinates":[57.45,-20.46667],"type":"Point"}
}