{
  "type": "Feature",
  "properties": {
    "gn:admin1_code":"17",
    "gn:asciiname":"Reunion",
    "gn:country_code":"MU",
    "gn:dem":430,
    "gn:feature_class":"P",
    "gn:feature_code":"PPL",
    "gn:name":"R\u00e9union",
    "gn:population":0,
    "gn:timezone":"Indian/Mauritius",
    "iso:country":"MU",
    "wof:name":"Reunion",
    "wof:placetype":"locality"
},
  "geometry": {"coordinates":[57.48806,-20.30917],"type":"Point"}
}