{
  "type": "Feature",
  "properties": {
    "gn:admin1_code":"15",
    "gn:asciiname":"L'Escalier",
    "gn:country_code":"MU",
    "gn:dem":467,
    "gn:feature_class":"P",
    "gn:feature_code":"PPL",
    "gn:name":"L\u2019Escalier",
    "gn:population":0,
    "gn:timezone":"Indian/Mauritius",
    "iso:country":"MU",
    "wof:name":"L'Escalier",
    "wof:placetype":"locality"
},
  "geometry": {"coordinates":[57.58221999999999,-20.19],"type":"Point"}
}